<?xml version="1.0" ?><ItemLookupResponse xmlns="http://webservices.amazon.com/AWSECommerceService/2011-08-01"><OperationRequest><HTTPHeaders><Header Name="UserAgent" Value="Java/1.8.0_144"></Header></HTTPHeaders><RequestId>a5ccb291-674a-4f35-97d0-ca17bd97e733</RequestId><Arguments><Argument Name="AWSAccessKeyId" Value="AKIAILOKWGJSK5XTCR2A"></Argument><Argument Name="AssociateTag" Value="330ed-20"></Argument><Argument Name="ItemId" Value="5553344867"></Argument><Argument Name="Operation" Value="ItemLookup"></Argument><Argument Name="ResponseGroup" Value="Large"></Argument><Argument Name="Service" Value="AWSECommerceService"></Argument><Argument Name="Timestamp" Value="2017-12-05T08:22:24Z"></Argument><Argument Name="Version" Value="2011-08-01"></Argument><Argument Name="Signature" Value="/6WdUbKwBaZm8gQ+FMsGHp7YiGBQcCWcVFGyngUSMuc="></Argument></Arguments><RequestProcessingTime>0.0564254180000000</RequestProcessingTime></OperationRequest><Items><Request><IsValid>True</IsValid><ItemLookupRequest><IdType>ASIN</IdType><ItemId>5553344867</ItemId><ResponseGroup>Large</ResponseGroup><VariationPage>All</VariationPage></ItemLookupRequest></Request><Item><ASIN>5553344867</ASIN><DetailPageURL>https://www.amazon.com/Dont-Say-Word-Michael-Douglas/dp/5553344867?SubscriptionId=AKIAILOKWGJSK5XTCR2A&amp;tag=330ed-20&amp;linkCode=xm2&amp;camp=2025&amp;creative=165953&amp;creativeASIN=5553344867</DetailPageURL><ItemLinks><ItemLink><Description>Technical Details</Description><URL>https://www.amazon.com/Dont-Say-Word-Michael-Douglas/dp/tech-data/5553344867?SubscriptionId=AKIAILOKWGJSK5XTCR2A&amp;tag=330ed-20&amp;linkCode=xm2&amp;camp=2025&amp;creative=386001&amp;creativeASIN=5553344867</URL></ItemLink><ItemLink><Description>Add To Baby Registry</Description><URL>https://www.amazon.com/gp/registry/baby/add-item.html?asin.0=5553344867&amp;SubscriptionId=AKIAILOKWGJSK5XTCR2A&amp;tag=330ed-20&amp;linkCode=xm2&amp;camp=2025&amp;creative=386001&amp;creativeASIN=5553344867</URL></ItemLink><ItemLink><Description>Add To Wedding Registry</Description><URL>https://www.amazon.com/gp/registry/wedding/add-item.html?asin.0=5553344867&amp;SubscriptionId=AKIAILOKWGJSK5XTCR2A&amp;tag=330ed-20&amp;linkCode=xm2&amp;camp=2025&amp;creative=386001&amp;creativeASIN=5553344867</URL></ItemLink><ItemLink><Description>Add To Wishlist</Description><URL>https://www.amazon.com/gp/registry/wishlist/add-item.html?asin.0=5553344867&amp;SubscriptionId=AKIAILOKWGJSK5XTCR2A&amp;tag=330ed-20&amp;linkCode=xm2&amp;camp=2025&amp;creative=386001&amp;creativeASIN=5553344867</URL></ItemLink><ItemLink><Description>Tell A Friend</Description><URL>https://www.amazon.com/gp/pdp/taf/5553344867?SubscriptionId=AKIAILOKWGJSK5XTCR2A&amp;tag=330ed-20&amp;linkCode=xm2&amp;camp=2025&amp;creative=386001&amp;creativeASIN=5553344867</URL></ItemLink><ItemLink><Description>All Customer Reviews</Description><URL>https://www.amazon.com/review/product/5553344867?SubscriptionId=AKIAILOKWGJSK5XTCR2A&amp;tag=330ed-20&amp;linkCode=xm2&amp;camp=2025&amp;creative=386001&amp;creativeASIN=5553344867</URL></ItemLink><ItemLink><Description>All Offers</Description><URL>https://www.amazon.com/gp/offer-listing/5553344867?SubscriptionId=AKIAILOKWGJSK5XTCR2A&amp;tag=330ed-20&amp;linkCode=xm2&amp;camp=2025&amp;creative=386001&amp;creativeASIN=5553344867</URL></ItemLink></ItemLinks><ItemAttributes><Actor>Michael Douglas</Actor><Actor>Oliver Platt</Actor><Binding>VHS Tape</Binding><Director>Gary Fleder</Director><EAN>9785553344863</EAN><EANList><EANListElement>9785553344863</EANListElement></EANList><Format>NTSC</Format><ISBN>5553344867</ISBN><ItemDimensions><Height Units="hundredths-inches">70</Height><Length Units="hundredths-inches">540</Length><Weight Units="hundredths-pounds">46</Weight><Width Units="hundredths-inches">750</Width></ItemDimensions><Label>Twentieth Century-Fox</Label><Languages><Language><Name>English</Name><Type>Unknown</Type></Language></Languages><ListPrice><Amount>698</Amount><CurrencyCode>USD</CurrencyCode><FormattedPrice>$6.98</FormattedPrice></ListPrice><Manufacturer>Twentieth Century-Fox</Manufacturer><NumberOfDiscs>1</NumberOfDiscs><NumberOfItems>1</NumberOfItems><PackageDimensions><Height Units="hundredths-inches">70</Height><Length Units="hundredths-inches">750</Length><Weight Units="hundredths-pounds">46</Weight><Width Units="hundredths-inches">540</Width></PackageDimensions><ProductGroup>Video</ProductGroup><ProductTypeName>ABIS_VIDEO</ProductTypeName><PublicationDate>2005-09</PublicationDate><Publisher>Twentieth Century-Fox</Publisher><Studio>Twentieth Century-Fox</Studio><Title>Don't Say a Word [VHS]</Title></ItemAttributes><OfferSummary><TotalNew>0</TotalNew><TotalUsed>0</TotalUsed><TotalCollectible>0</TotalCollectible><TotalRefurbished>0</TotalRefurbished></OfferSummary><Offers><TotalOffers>0</TotalOffers><TotalOfferPages>0</TotalOfferPages><MoreOffersUrl>0</MoreOffersUrl></Offers><CustomerReviews><IFrameURL>https://www.amazon.com/reviews/iframe?akid=AKIAILOKWGJSK5XTCR2A&amp;alinkCode=xm2&amp;asin=5553344867&amp;atag=330ed-20&amp;exp=2017-12-06T08%3A22%3A25Z&amp;v=2&amp;sig=Aeh3YIt1rg6uYLbF6POeyZeMdFi7DfN7ahMTvJrdknQ%253D</IFrameURL><HasReviews>true</HasReviews></CustomerReviews><BrowseNodes><BrowseNode><BrowseNodeId>2649512011</BrowseNodeId><Name>Movies</Name><Ancestors><BrowseNode><BrowseNodeId>2625374011</BrowseNodeId><Name>Departments</Name><IsCategoryRoot>1</IsCategoryRoot><Ancestors><BrowseNode><BrowseNodeId>2625373011</BrowseNodeId><Name>Movies &amp; TV</Name></BrowseNode></Ancestors></BrowseNode></Ancestors></BrowseNode><BrowseNode><BrowseNodeId>2958767011</BrowseNodeId><Name>Drama</Name><Ancestors><BrowseNode><BrowseNodeId>2958761011</BrowseNodeId><Name>Genre for Featured Categories</Name><Ancestors><BrowseNode><BrowseNodeId>2644982011</BrowseNodeId><Name>Custom Stores</Name><Ancestors><BrowseNode><BrowseNodeId>2644981011</BrowseNodeId><Name>Specialty Stores</Name><Ancestors><BrowseNode><BrowseNodeId>2625373011</BrowseNodeId><Name>Movies &amp; TV</Name></BrowseNode></Ancestors></BrowseNode></Ancestors></BrowseNode></Ancestors></BrowseNode></Ancestors></BrowseNode><BrowseNode><BrowseNodeId>2958772011</BrowseNodeId><Name>Mystery &amp; Thrillers</Name><Ancestors><BrowseNode><BrowseNodeId>2958761011</BrowseNodeId><Name>Genre for Featured Categories</Name><Ancestors><BrowseNode><BrowseNodeId>2644982011</BrowseNodeId><Name>Custom Stores</Name><Ancestors><BrowseNode><BrowseNodeId>2644981011</BrowseNodeId><Name>Specialty Stores</Name><Ancestors><BrowseNode><BrowseNodeId>2625373011</BrowseNodeId><Name>Movies &amp; TV</Name></BrowseNode></Ancestors></BrowseNode></Ancestors></BrowseNode></Ancestors></BrowseNode></Ancestors></BrowseNode></BrowseNodes></Item></Items></ItemLookupResponse>